examples/__init__.py
examples/logger_screenstr.py
examples/logmeter.py
examples/save_example.py
examples/screenstrs.py
examples/templete.py
torchhelper/__init__.py
torchhelper/importing.py
torchhelper/base/__init__.py
torchhelper/base/meta.py
torchhelper/base/recordable.py
torchhelper/base/structure.py
torchhelper/cacu/__init__.py
torchhelper/cacu/accuracy.py
torchhelper/frame/__init__.py
torchhelper/frame/callbacks.py
torchhelper/frame/databundler.py
torchhelper/frame/logger.py
torchhelper/frame/logwrapper.py
torchhelper/frame/parameter.py
torchhelper/frame/saver.py
torchhelper/frame/trainer.py
torchhelper/frame/trainerv2.py
torchhelper/tune/__init__.py
torchhelper/tune/branch.py
torchhelper/tune/lossw.py
torchhelper/tune/optim.py
torchhelper-0.3.5.1.dev1.dist-info/LICENSE
torchhelper-0.3.5.1.dev1.dist-info/METADATA
torchhelper-0.3.5.1.dev1.dist-info/WHEEL
torchhelper-0.3.5.1.dev1.dist-info/entry_points.txt
torchhelper-0.3.5.1.dev1.dist-info/top_level.txt
torchhelper-0.3.5.1.dev1.dist-info/RECORD
