Metadata-Version: 2.1
Name: torchhelper
Version: 0.3.5.1.dev1
Summary: A torch helper for control log、train process（train/test/eval/checkpoint/save）
Home-page: https://github.com/sailist/TorchHelper
Author: sailist
Author-email: sailist@outlook.com
License: Apache License 2.0
Keywords: torchhelper
Platform: UNKNOWN
Classifier: Development Status :: 3 - Alpha
Classifier: Intended Audience :: Developers
Classifier: Topic :: Software Development :: Build Tools
Classifier: License :: OSI Approved :: Apache Software License
Classifier: Programming Language :: Python :: 3
Classifier: Programming Language :: Python :: 3.5
Requires-Dist: torch
Requires-Dist: fire
Requires-Dist: tensorboard
